common/v1/pagination_pb2.py
common/v1/pagination_pb2_grpc.py
common/v1/types_pb2.py
common/v1/types_pb2_grpc.py
data/v1/dataset_pb2.py
data/v1/dataset_pb2_grpc.py
data/v1/file_pb2.py
data/v1/file_pb2_grpc.py
data/v2/dataset_pb2.py
data/v2/dataset_pb2_grpc.py
deploy/v1/deploy_pb2.py
deploy/v1/deploy_pb2_grpc.py
orchestration/v1/model_list_pb2.py
orchestration/v1/model_list_pb2_grpc.py
orchestration/v1/user_model_pb2.py
orchestration/v1/user_model_pb2_grpc.py
user/v1/user_pb2.py
user/v1/user_pb2_grpc.py
drills_pro_proto-0.52.0.dist-info/METADATA
drills_pro_proto-0.52.0.dist-info/WHEEL
drills_pro_proto-0.52.0.dist-info/top_level.txt
drills_pro_proto-0.52.0.dist-info/RECORD
