Metadata-Version: 2.4
Name: drills-pro-proto
Version: 0.52.0
Summary: Protocol Buffers for drills.pro
Requires-Python: >=3.10
Requires-Dist: protobuf==3.20.3
